FileNet/__init__.py
FileNet/main.py
FileNet-1.1.5.dist-info/METADATA
FileNet-1.1.5.dist-info/WHEEL
FileNet-1.1.5.dist-info/entry_points.txt
FileNet-1.1.5.dist-info/top_level.txt
FileNet-1.1.5.dist-info/RECORD
