Metadata-Version: 2.1
Name: FileNet
Version: 1.1.5
Summary: A Python package for creating 2D, 3D vizulization of directory and files with their hierarchical relations.
Author: Aditya Narayan
Author-email: adityaan277@gmail.com
Requires-Dist: networkx
Requires-Dist: matplotlib
Requires-Dist: plotly
Requires-Dist: scipy
